schemax/__init__.py
schemax/__main__.py
schemax/__version__.py
schemax/_config.py
schemax/_data_collector.py
schemax/_from_json_schema.py
schemax/_generator.py
schemax/_interface.py
schemax/_openapi_normalizer.py
schemax/_translator.py
schemax/py.typed
schemax/supported_props.py
schemax/templates/api_route.py.j2
schemax/templates/interfaces.py.j2
schemax/templates/scenario.py.j2
schemax/templates/schema_definition.py.j2
schemax/templates/schemas.py.j2
schemax-2.1.1.data/data/schemax/py.typed
schemax-2.1.1.dist-info/METADATA
schemax-2.1.1.dist-info/WHEEL
schemax-2.1.1.dist-info/entry_points.txt
schemax-2.1.1.dist-info/licenses/LICENSE.txt
schemax-2.1.1.dist-info/RECORD
