Metadata-Version: 2.4
Name: schemax
Version: 2.1.1
Summary: d42 to JSON-Schema translator and vise versa
Project-URL: Homepage, https://github.com/Lolimpo/schemax
Project-URL: Repository, https://github.com/Lolimpo/schemax
Author-email: Nikita Mikheev <thelol1mpo@gmail.com>
License: 
License-File: LICENSE.txt
Classifier: License :: OSI Approved :: Apache Software License
Classifier: Programming Language :: Python :: 3.10
Classifier: Programming Language :: Python :: 3.11
Classifier: Programming Language :: Python :: 3.12
Classifier: Programming Language :: Python :: 3.13
Classifier: Typing :: Typed
Requires-Python: >=3.10
Requires-Dist: d42<3.0.0,>=2.0.0
Requires-Dist: district42-exp-types<2.0.0,>=1.0.0
Requires-Dist: jinja2<4.0.0,>=3.1.5
Requires-Dist: niltype<2.0.0,>=0.3.4
Requires-Dist: pyyaml<7.0.0,>=6.0.1
Requires-Dist: referencing<1.0.0,>=0.35.1
Requires-Dist: vedro-httpx<1.0.0,>=0.0.1
Requires-Dist: vedro<2.0.0,>=1.0.0
